{
    "Aturan Anti Cinta": {
        "Centers": [
            {
                "Center": "Marsha",
                "Blocking 2" : "Fiony, Jessi, Lulu",
                "Blocking 3" : "Christy, Muthe, Indah, Greesel",
                "Blocking 4" : "Gracia, Olla, Lia",
                "Blocking 5" : "Lulu, Jessi, Lyn",
                "Blocking 6" : "Freya, Indira, Gracie, Raisha",
                "Blocking 7" : "Kathrina, Eli, Danella",
                "Blocking 8" : "Freya, Gita, Amanda, Greesel",
                "Blocking 9" : "Gita, Kathrina, Lulu, Ella, Daisy, Regie",
                "Blocking 10" : "Oniel, Indah, Gracie, Michie, Erine, Fritzy",
                "Blocking 11" : "Jessi, Lia, Cathy, Lily",
                "Blocking 12" : "Cynthia, Alya, Elin, Delynn",
                "Blocking 13" : "Indah, Raisha, Danella, Nachia",
                "Blocking 14" : "Eli, Oniel, Lulu, Amanda, Gendis, Ribka",
                "Blocking 15" : "Indira, Chelsea, Levi",
                "Blocking 16" : "Olla, Lyn, Anin, Aralie, Lana"
                
            },
            {
                "Center": "Oniel",
                "Blocking 2" : "Fiony, Jessi, Lulu",
                "Blocking 3" : "Christy, Muthe, Indah, Greesel",
                "Blocking 4" : "Gracia, Olla, Lia",
                "Blocking 5" : "Lulu, Jessi, Lyn",
                "Blocking 6" : "Freya, Indira, Gracie, Raisha",
                "Blocking 7" : "Kathrina, Eli, Danella",
                "Blocking 8" : "Freya, Gita, Amanda, Greesel",
                "Blocking 9" : "Gita, Kathrina, Lulu, Ella, Daisy, Regie",
                "Blocking 10" : "Oniel, Indah, Gracie, Michie, Erine, Fritzy",
                "Blocking 11" : "Jessi, Lia, Cathy, Lily",
                "Blocking 12" : "Cynthia, Alya, Elin, Delynn",
                "Blocking 13" : "Indah, Raisha, Danella, Nachia",
                "Blocking 14" : "Eli, Lulu, Amanda, Gendis, Ribka",
                "Blocking 15" : "Marsha, Indira, Chelsea, Levi",
                "Blocking 16" : "Olla, Lyn, Anin, Aralie, Lana"
            },
            {
                "Center": "Muthe",
                "Blocking 2" : "Fiony, Jessi, Lulu",
                "Blocking 3" : "Christy, Indah, Greesel",
                "Blocking 4" : "Gracia, Olla, Lia",
                "Blocking 5" : "Lulu, Jessi, Lyn",
                "Blocking 6" : "Freya, Indira, Gracie, Raisha",
                "Blocking 7" : "Kathrina, Eli, Danella",
                "Blocking 8" : "Freya, Gita, Amanda, Greesel",
                "Blocking 9" : "Gita, Kathrina, Lulu, Ella, Daisy, Regie",
                "Blocking 10" : "Oniel, Indah, Gracie, Michie, Erine, Fritzy",
                "Blocking 11" : "Jessi, Lia, Cathy, Lily",
                "Blocking 12" : "Cynthia, Alya, Elin, Delynn",
                "Blocking 13" : "Indah, Raisha, Danella, Nachia",
                "Blocking 14" : "Eli, Oniel, Lulu, Amanda, Gendis, Ribka",
                "Blocking 15" : "Marsha, Indira, Chelsea, Levi",
                "Blocking 16" : "Olla, Lyn, Anin, Aralie, Lana"
            },
            {
                "Center": "Feni",
                "Blocking 2" : "Fiony, Jessi, Lulu",
                "Blocking 3" : "Christy, Muthe, Indah, Greesel",
                "Blocking 4" : "Gracia, Olla, Lia",
                "Blocking 5" : "Lulu, Jessi, Lyn",
                "Blocking 6" : "Freya, Indira, Gracie, Raisha",
                "Blocking 7" : "Kathrina, Eli, Danella",
                "Blocking 8" : "Freya, Gita, Amanda, Greesel",
                "Blocking 9" : "Gita, Kathrina, Lulu, Ella, Daisy, Regie",
                "Blocking 10" : "Oniel, Indah, Gracie, Michie, Erine, Fritzy",
                "Blocking 11" : "Jessi, Lia, Cathy, Lily",
                "Blocking 12" : "Cynthia, Alya, Elin, Delynn",
                "Blocking 13" : "Indah, Raisha, Danella, Nachia",
                "Blocking 14" : "Eli, Oniel, Lulu, Amanda, Gendis, Ribka",
                "Blocking 15" : "Marsha, Indira, Chelsea, Levi",
                "Blocking 16" : "Olla, Lyn, Anin, Aralie, Lana"  
            },
            {
                "Center": "Indah",
                "Blocking 2" : "Fiony, Jessi, Lulu",
                "Blocking 3" : "Christy, Muthe, Greesel",
                "Blocking 4" : "Gracia, Olla, Lia",
                "Blocking 5" : "Lulu, Jessi, Lyn",
                "Blocking 6" : "Freya, Indira, Gracie, Raisha",
                "Blocking 7" : "Kathrina, Eli, Danella",
                "Blocking 8" : "Freya, Gita, Amanda, Greesel",
                "Blocking 9" : "Gita, Kathrina, Lulu, Ella, Daisy, Regie",
                "Blocking 10" : "Oniel, Gracie, Michie, Erine, Fritzy",
                "Blocking 11" : "Jessi, Lia, Cathy, Lily",
                "Blocking 12" : "Cynthia, Alya, Elin, Delynn",
                "Blocking 13" : "Indah, Raisha, Danella, Nachia",
                "Blocking 14" : "Eli, Oniel, Lulu, Amanda, Gendis, Ribka",
                "Blocking 15" : "Marsha, Indira, Chelsea, Levi",
                "Blocking 16" : "Olla, Lyn, Anin, Aralie, Lana"  
            }
        ]
    },
    "Cara Meminum Ramune": {
        "Centers": [
            {
                "Yellow": "Fiony",
                "Pink" : "Gracia, Jessi",
                "Bronze" : "Marsha, Oniel",
                "Green" : "Muthe",
                "Emerald" : "Feni, Kathrina, Ella",
                "Azure" : "Gita",
                "Lilac" : "Jessi, Olla, Lia",
                "Coral" : "Muthe, Greesel, Nala",
                "Magenta" : "Indah, Amanda, Cathy, Gendis, Nayla",
                "Sky blue" : "Kathrina, Lia, Cynthia, Chelsea",
                "Maroon" : "Lulu, Raisha, Elin, Fritzy",
                "Apricot" : "Freya, Ella, Gracie, Alya",
                "Lime" : "Indira, Lyn",
                "Baby blue" : "Oniel, Indira, Michie, Anin, Lana",
                "Navy" : "Marsha, Danella, Lyn, Oline",
                "Lavender" : "Eli, Daisy, Kimmy"
            },
            {
                "Yellow": "Christy",
                "Pink" : "Gracia, Jessi",
                "Bronze" : "Marsha, Oniel",
                "Green" : "Muthe",
                "Emerald" : "Feni, Kathrina, Ella",
                "Azure" : "Gita",
                "Lilac" : "Jessi, Olla, Lia",
                "Coral" : "Muthe, Greesel, Nala",
                "Magenta" : "Indah, Amanda, Cathy, Gendis, Nayla",
                "Sky blue" : "Kathrina, Lia, Cynthia, Chelsea",
                "Maroon" : "Fiony, Lulu, Raisha, Elin, Fritzy",
                "Apricot" : "Freya, Ella, Gracie, Alya",
                "Lime" : "Indira, Lyn",
                "Baby blue" : "Oniel, Indira, Michie, Anin, Lana",
                "Navy" : "Marsha, Danella, Lyn, Oline",
                "Lavender" : "Eli, Daisy, Kimmy"
            },
            {
                "Yellow": "Kathrina",
                "Pink" : "Gracia, Jessi",
                "Bronze" : "Marsha, Oniel",
                "Green" : "Muthe",
                "Emerald" : "Feni, Ella",
                "Azure" : "Gita",
                "Lilac" : "Jessi, Olla, Lia",
                "Coral" : "Muthe, Greesel, Nala",
                "Magenta" : "Indah, Amanda, Cathy, Gendis, Nayla",
                "Sky blue" : "Lia, Cynthia, Chelsea",
                "Maroon" : "Fiony, Lulu, Raisha, Elin, Fritzy",
                "Apricot" : "Freya, Ella, Gracie, Alya",
                "Lime" : "Indira, Lyn",
                "Baby blue" : "Oniel, Indira, Michie, Anin, Lana",
                "Navy" : "Marsha, Danella, Lyn, Oline",
                "Lavender" : "Eli, Daisy, Kimmy"
            }
        ]
    },
    "Ingin Bertemu": {
        "Centers": [
            {
                "Center": "Trisha",
                "Blocking 2": "Nachia, Erine",
                "Blocking 3": "Oline, Delynn",
                "Blocking 4": "Nayla, Nala, Jemima",
                "Blocking 5": "Ribka, Delynn, Intan",
                "Blocking 6": "Kimmy, Ekin",
                "Blocking 7": "Levi, Nala, Maira",
                "Blocking 8": "Erine, Mikaela",
                "Blocking 9": "Regie, Delynn, Giaa",
                "Blocking 10": "Aralie, Auwia",
                "Blocking 11": "Lily, Rilly",
                "Blocking 12": "Virgi"
            }
        ]
    },
    "Pajama Drive": {
        "Centers": [
            {
                "Center": "Trisha",
                "Blocking 2": "Nayla, Erine",
                "Blocking 3": "Levi, Delynn, Jemima",
                "Blocking 4": "Oline",
                "Blocking 5": "Regie, Auwia",
                "Blocking 6": "Kimmy, Maira",
                "Blocking 7": "Ekin",
                "Blocking 8": "Intan",
                "Blocking 9": "Lily, Virgi",
                "Blocking 10": "Nala, Giaa",
                "Blocking 11": "Aralie, Erine. Mikaela",
                "Blocking 12": "Nachia, Ribka, Rilly"
            }
        ]
    },
    "Sambil Menggandeng Erat Tanganku": {
        "Centers": [
            {
                "Center": "Freya",
                "Blocking 2": "Christy, Marsha, Muthe",
                "Blocking 3": "Fiony, Gita, Feni",
                "Blocking 4": "Gracia, Jessi, Kathrina",
                "Blocking 5": "Olla, Gracie, Danella, Fritzy",
                "Blocking 6": "Greesel, Eli, Oniel, Erine",
                "Blocking 7": "Lulu, Lia, Cathy",
                "Blocking 8": "Lyn, Raisha, Indah",
                "Blocking 9": "Indira, Amanda, Danella, Regie",
                "Blocking 10": "Cynthia, Gendis, Nala, Lana",
                "Blocking 11": "Elin, Chelsea, Daisy, Kimmy",
                "Blocking 12": "Alya, Anin, Ribka"
            },
            {
                "Center": "Ella",
                "Blocking 2": "Christy, Marsha, Muthe",
                "Blocking 3": "Fiony, Gita, Feni",
                "Blocking 4": "Gracia, Jessi, Kathrina",
                "Blocking 5": "Olla, Gracie, Danella, Fritzy",
                "Blocking 6": "Greesel, Eli, Oniel, Erine",
                "Blocking 7": "Lulu, Lia, Cathy",
                "Blocking 8": "Lyn, Raisha, Indah",
                "Blocking 9": "Indira, Amanda, Danella, Regie",
                "Blocking 10": "Cynthia, Gendis, Nala, Lana",
                "Blocking 11": "Elin, Chelsea, Daisy, Kimmy",
                "Blocking 12": "Alya, Anin, Ribka"
            },
            {
                "Center": "Michie",
                "Blocking 2": "Christy, Marsha, Muthe",
                "Blocking 3": "Fiony, Gita, Feni",
                "Blocking 4": "Gracia, Jessi, Kathrina",
                "Blocking 5": "Olla, Gracie, Danella, Fritzy",
                "Blocking 6": "Greesel, Eli, Oniel, Erine",
                "Blocking 7": "Lulu, Lia, Cathy",
                "Blocking 8": "Lyn, Raisha, Indah",
                "Blocking 9": "Indira, Amanda, Danella, Regie",
                "Blocking 10": "Cynthia, Gendis, Nala, Lana",
                "Blocking 11": "Elin, Chelsea, Daisy, Kimmy",
                "Blocking 12": "Alya, Anin, Ribka"
            }
        ]
    }
}
